dict2obj/__init__.py
dict2obj/converter.py
dict2obj/py.typed
dict2objects-0.1.4.dist-info/LICENSE
dict2objects-0.1.4.dist-info/METADATA
dict2objects-0.1.4.dist-info/WHEEL
dict2objects-0.1.4.dist-info/RECORD
