Metadata-Version: 2.3
Name: dict2objects
Version: 0.1.4
Summary: Convert dictionaries into objects with attribute-style access
License: MIT
Keywords: dictionary,object,conversion,dot,access
Author: Janardhan Singh
Author-email: janardhansingh1998@gmail.com
Requires-Python: >=3.8,<4.0
Classifier: Programming Language :: Python :: 3
Classifier: License :: OSI Approved :: MIT License
Classifier: Operating System :: OS Independent
Project-URL: Documentation, https://github.com/JanardhanSingh98/dict2obj
Project-URL: Homepage, https://github.com/JanardhanSingh98/dict2obj
Project-URL: Issues, https://github.com/JanardhanSingh98/dict2obj/issues
Project-URL: Repository, https://github.com/JanardhanSingh98/dict2obj
